fastQuast/__init__.py
fastQuast/fastQuast.py
fastQuast/fastQuast.test.py
fastquast-1.2.3.dist-info/licenses/LICENSE
fastquast-1.2.3.dist-info/METADATA
fastquast-1.2.3.dist-info/WHEEL
fastquast-1.2.3.dist-info/entry_points.txt
fastquast-1.2.3.dist-info/top_level.txt
fastquast-1.2.3.dist-info/RECORD
